LICENSE
MANIFEST.in
README.md
setup.py
pydgeot/__init__.py
pydgeot/generator.py
pydgeot/observer.py
pydgeot.egg-info/PKG-INFO
pydgeot.egg-info/SOURCES.txt
pydgeot.egg-info/dependency_links.txt
pydgeot.egg-info/top_level.txt
pydgeot/app/__init__.py
pydgeot/app/contexts.py
pydgeot/app/dirconfig.py
pydgeot/app/sources.py
pydgeot/commands/__init__.py
pydgeot/commands/builtins/__init__.py
pydgeot/commands/builtins/build.py
pydgeot/commands/builtins/clean.py
pydgeot/commands/builtins/create.py
pydgeot/commands/builtins/list_commands.py
pydgeot/commands/builtins/list_plugins.py
pydgeot/commands/builtins/list_processors.py
pydgeot/commands/builtins/reset.py
pydgeot/commands/builtins/watch.py
pydgeot/filesystem/__init__.py
pydgeot/filesystem/glob.py
pydgeot/processors/__init__.py
pydgeot/processors/builtins/__init__.py
pydgeot/processors/builtins/copyfallback.py
pydgeot/processors/builtins/symlinkfallback.py
scripts/pydgeot
tests/conftest.py
tests/setup.cfg
tests/test_app.py
tests/test_contexts.py
tests/test_dirconfig.py
tests/test_filesystem.py
tests/test_generator.py
tests/test_glob.py
tests/test_sources.py
tests/resources/app_new/pydgeot.conf
tests/resources/test_dirconfig/pydgeot.conf
tests/resources/test_dirconfig/source/.pydgeot.conf
tests/resources/test_dirconfig/source/sub/.pydgeot.conf
tests/resources/test_generator/expected_build_delete/index.txt
tests/resources/test_generator/expected_build_generate/index.txt
tests/resources/test_generator/expected_build_generate/sub/subindex.txt
tests/resources/test_generator/source_app/pydgeot.conf
tests/resources/test_generator/source_app/source/index.txt
tests/resources/test_generator/source_app/source/no.ignore
tests/resources/test_generator/source_app/source/sub/no.ignore
tests/resources/test_generator/source_app/source/sub/subindex.txt