Metadata-Version: 1.1
Name: pydgeot
Version: 1.0b1
Summary: Plugin based static content generator
Home-page: https://github.com/broiledmeat/pydgeot
Author: Derrick Staples
Author-email: broiledmeat@gmail.com
License: Apache License, Version 2.0
Platform: UNKNOWN
Classifier: Intended Audience :: Developers
Classifier: License :: OSI Approved :: Apache Software License
Classifier: Operating System :: OS Independent
Classifier: Programming Language :: Python :: 3.5
Classifier: Topic :: Software Development :: Libraries :: Python Modules
Requires: docopt
